MANIFEST.in
README.md
setup.py
pline/__init__.py
pline/actions.py
pline/activities.py
pline/base.py
pline/data_formats.py
pline/data_nodes.py
pline/databases.py
pline/exceptions.py
pline/keywords.py
pline/parameters.py
pline/pipeline.py
pline/preconditons.py
pline/resources.py
pline/utils.py
pline.egg-info/PKG-INFO
pline.egg-info/SOURCES.txt
pline.egg-info/dependency_links.txt
pline.egg-info/requires.txt
pline.egg-info/top_level.txt